AUTHORS.rst
CHANGELOG.rst
LICENSE
MANIFEST.in
README.rst
setup.py
jmbo_neo.egg-info/PKG-INFO
jmbo_neo.egg-info/SOURCES.txt
jmbo_neo.egg-info/dependency_links.txt
jmbo_neo.egg-info/not-zip-safe
jmbo_neo.egg-info/requires.txt
jmbo_neo.egg-info/top_level.txt
neo/__init__.py
neo/api.py
neo/constants.py
neo/forms.py
neo/models.py
neo/test_urls.py
neo/tests.py
neo/utils.py
neo/validation.py
neo/xml.py
neo/management/__init__.py
neo/management/commands/__init__.py
neo/management/commands/members_to_cidb_dataloadtool.py
neo/migrations/0001_initial.py
neo/migrations/0002_auto__chg_field_neoprofile_user.py
neo/migrations/0003_auto__add_field_neoprofile_login_alias.py
neo/migrations/0004_set_login_alias.py
neo/migrations/0005_add_field_neoprofile_login_alias.py
neo/migrations/0006_auto__add_field_neoprofile_password.py
neo/migrations/0007_reset_passwords.py
neo/migrations/0008_auto__add_field_neoprofile_created.py
neo/migrations/__init__.py